LAB 1/PrimeDetector/PrimeDetector.vhd
library ieee; 
use ieee.std_logic_1164.all;

entity primedetector is
    port ( sw: in bit_vector (3 downto 0);         -- array of bits
        prime : out bit);                          -- 0 or 1
end primedetector; 

architecture primearch of primedetector is

    -- let n3 = sw(3), cn3 = not sw(3); n2 = sw(2), cn2 = not sw(2)...
    signal cn3_n2_n0, cn3_cn2_n1, cn2_n1_n0, n2_cn1_n0: bit;    -- bit containers
    begin
        cn3_n2_n0  <= not sw(3)    and     sw(2)                   and sw(0);
        cn3_cn2_n1 <= not sw(3)    and not sw(2)   and     sw(1)            ;
        cn2_n1_n0  <=                  not sw(2)   and     sw(1)   and sw(0);
        n2_cn1_n0  <=                      sw(2)   and not sw(1)   and sw(0);

        prime <= cn3_n2_n0 or cn3_cn2_n1 or cn2_n1_n0 or n2_cn1_n0;
end primearch;

LAB 1/PrimeDetector/PrimeDetector_TB.vhd
entity PrimeDetector_TB is
end entity;

architecture PrimeDetector_TB_arch of PrimeDetector_TB is

 -- Constant Declaration
  constant t_wait : time := 10 ns; 

 -- Component Declaration   
  component PrimeDetector
    port	(	SW		:	in	bit_vector (3 downto 0);
				Prime	: 	out	bit);
  end component;

 -- Signal Declaration
  signal   SW_TB  : bit_vector (3 downto 0); -- these signals are used to connect to the device under test (DUT)
  signal   Prime_TB              : bit;

  begin

 -- Component Instantiation of DUT
  DUT :   PrimeDetector
            port map (SW    => SW_TB,                    
                      Prime    => Prime_TB);

 -- Stimulus Generation
  STIMULUS : process
    begin
      SW_TB <= "0000"; wait for t_wait;
      SW_TB <= "0001"; wait for t_wait;
	  SW_TB <= "0010"; wait for t_wait;
	  SW_TB <= "0011"; wait for t_wait;
	  SW_TB <= "0100"; wait for t_wait;
	  SW_TB <= "0101"; wait for t_wait;
	  SW_TB <= "0110"; wait for t_wait;
	  SW_TB <= "0111"; wait for t_wait;
	  
	  SW_TB <= "1000"; wait for t_wait;
      SW_TB <= "1001"; wait for t_wait;
	  SW_TB <= "1010"; wait for t_wait;
	  SW_TB <= "1011"; wait for t_wait;
	  SW_TB <= "1100"; wait for t_wait;
	  SW_TB <= "1101"; wait for t_wait;
	  SW_TB <= "1110"; wait for t_wait;
	  SW_TB <= "1111"; wait for t_wait;
    end process;
      
end architecture;

LAB 1/PrimeDetector/PrimeDetector.vcd
$date
  Mon Mar 07 16:16:16 2022
$end
$version
  GHDL v0
$end
$timescale
  1 fs
$end
$scope module standard $end
$upscope $end
$scope module std_logic_1164 $end
$upscope $end
$scope module primedetector_tb $end
$var reg 4 ! sw_tb[3:0] $end
$var reg 1 " prime_tb $end
$scope module dut $end
$var reg 4 # sw[3:0] $end
$var reg 1 $ prime $end
$var reg 1 % cn3_n2_n0 $end
$var reg 1 & cn3_cn2_n1 $end
$var reg 1 ' cn2_n1_n0 $end
$var reg 1 ( n2_cn1_n0 $end
$upscope $end
$upscope $end
$enddefinitions $end
#0
b0000 !
0"
b0000 #
0$
0%
0&
0'
0(
#10000000
b0001 !
b0001 #
#20000000
b0010 !
1"
b0010 #
1$
1&
#30000000
b0011 !
b0011 #
1'
#40000000
b0100 !
0"
b0100 #
0$
0&
0'
#50000000
b0101 !
1"
b0101 #
1$
1%
1(
#60000000
b0110 !
0"
b0110 #
0$
0%
0(
#70000000
b0111 !
1"
b0111 #
1$
1%
#80000000
b1000 !
0"
b1000 #
0$
0%
#90000000
b1001 !
b1001 #
#100000000
b1010 !
b1010 #
#110000000
b1011 !
1"
b1011 #
1$
1'
#120000000
b1100 !
0"
b1100 #
0$
0'
#130000000
b1101 !
1"
b1101 #
1$
1(
#140000000
b1110 !
0"
b1110 #
0$
0(
#150000000
b1111 !
b1111 #
#160000000
b0000 !
b0000 #
